{
  "$schema": "https://raw.githubusercontent.com/DotNetAnalyzers/StyleCopAnalyzers/master/StyleCop.Analyzers/StyleCop.Analyzers/Settings/stylecop.schema.json",
  "settings": {
    "documentationRules": {
      "companyName": "Battleship Coding Group",
      "copyrightText": "{companyName}, 2022",
      "xmlHeader": true,
      "headerDecoration": "-----------------------------------------------------------------------",

      "documentPrivateElements": true,
      "documentPrivateFields": true
    },
    "namingRules": {
      "allowCommonHungarianPrefixes": false
    }
  }
}